procstats/__init__.py
procstats/cli.py
procstats/cpp/combined_monitoring.cpp
procstats/cpp/cpu_ram_monitoring.cpp
procstats/cpp/gpu_monitoring.cpp
procstats/scripts/__init__.py
procstats/scripts/cpu_monitor_setup.py
procstats/scripts/cpu_ram_monitoring.py
procstats/scripts/cpu_test_lib.py
procstats/scripts/full_monitoring.py
procstats/scripts/gpu_monitor_setup.py
procstats/scripts/gpu_monitoring.py
procstats/scripts/gpu_test_lib.py
procstats/scripts/system_info.py
procstats/tests/test_burn_cpu_ram.py
procstats/tests/test_lib.py
procstats-0.2.0.dist-info/licenses/LICENSE
procstats-0.2.0.dist-info/METADATA
procstats-0.2.0.dist-info/WHEEL
procstats-0.2.0.dist-info/entry_points.txt
procstats-0.2.0.dist-info/top_level.txt
procstats-0.2.0.dist-info/RECORD
