Metadata-Version: 2.4
Name: procstats
Version: 0.2.0
Summary: A Python package for monitoring CPU, RAM, and GPU resources
Home-page: https://github.com/Mikyx-1/ProcStats
Author: Le Hoang Viet
Author-email: Le Hoang Viet <lehoangviet2k@gmail.com>
License: MIT License
Project-URL: Homepage, https://github.com/Mikyx-1/ProcStats
Project-URL: Repository, https://github.com/Mikyx-1/ProcStats
Project-URL: Issues, https://github.com/Mikyx-1/ProcStats/issues
Classifier: Programming Language :: Python :: 3
Classifier: License :: OSI Approved :: MIT License
Classifier: Operating System :: OS Independent
Requires-Python: >=3.8
License-File: LICENSE
Requires-Dist: psutil>=5.9.0
Requires-Dist: dill>=0.3.0
Provides-Extra: gpu
Requires-Dist: pynvml>=11.0.0; extra == "gpu"
Provides-Extra: test
Requires-Dist: pytest>=7.0.0; extra == "test"
Dynamic: author
Dynamic: home-page
Dynamic: license-file
Dynamic: requires-python
